{
  "Trigger": {
    "center": {
      "x": 815.75,
      "y": 1627.25
    },
    "radius": 10.0,
    "rotation": 0.0,
    "wire_thickness": 0.0,
    "scale_x": 1.0,
    "scale_y": 1.0,
    "is_timer_enabled": false,
    "timer_interval": 100,
    "material": "",
    "surface": "",
    "is_visible": false,
    "is_enabled": true,
    "hit_height": 50.0,
    "name": "sw60",
    "shape": 0,
    "anim_speed": 1.0,
    "is_reflection_enabled": false,
    "drag_points": [
      {
        "x": 786.0,
        "y": 1567.5,
        "z": 0.0,
        "smooth": false,
        "is_slingshot": false,
        "has_auto_texture": true,
        "tex_coord": 0.0,
        "is_locked": false,
        "editor_layer": 0,
        "editor_layer_name": null,
        "editor_layer_visibility": null
      },
      {
        "x": 785.75,
        "y": 1657.25,
        "z": 0.0,
        "smooth": false,
        "is_slingshot": false,
        "has_auto_texture": true,
        "tex_coord": 0.0,
        "is_locked": false,
        "editor_layer": 0,
        "editor_layer_name": null,
        "editor_layer_visibility": null
      },
      {
        "x": 837.25,
        "y": 1657.25,
        "z": 0.0,
        "smooth": false,
        "is_slingshot": false,
        "has_auto_texture": true,
        "tex_coord": 0.0,
        "is_locked": false,
        "editor_layer": 0,
        "editor_layer_name": null,
        "editor_layer_visibility": null
      },
      {
        "x": 837.25,
        "y": 1567.5,
        "z": 0.0,
        "smooth": false,
        "is_slingshot": false,
        "has_auto_texture": true,
        "tex_coord": 0.0,
        "is_locked": false,
        "editor_layer": 0,
        "editor_layer_name": null,
        "editor_layer_visibility": null
      }
    ]
  }
}